clearshare/__init__.py
clearshare/app.py
clearshare/clearshare_app.py
clearshare/ipfs.py
clearshare-0.1.1.data/scripts/app.py
clearshare-0.1.1.data/scripts/clearshare_app.py
docker/Dockerfile
docker/docker-compose.yml
docker/hosts
docker/deploy/clearshare-volumes.py
docker/deploy/ipfs.yml
docker/deploy/requirements.txt
docker/deploy/wait-for-ipfs.sh
docker/specs/api.yml
docker/specs/ipfs.yml
docker/specs/global/model-pagination.yml
docker/specs/global/parsers-pagination.yml
docker/specs/ipfs/addoptions.yml
docker/specs/ipfs/models.yml
docker/specs/ipfs/namespaces.yml
docker/specs/ipfs/parsers.yml
clearshare-0.1.1.dist-info/METADATA
clearshare-0.1.1.dist-info/WHEEL
clearshare-0.1.1.dist-info/top_level.txt
clearshare-0.1.1.dist-info/RECORD
