Metadata-Version: 2.1
Name: clearshare
Version: 0.1.1
Summary: Data management REST API for ClearSHARE.
Home-page: https://gitlab.com/clearos/clearfoundation/clearshare
Author: ClearFoundation
Author-email: developer@clearfoundation.com
License: GPL-3.0
Platform: UNKNOWN
Classifier: Development Status :: 2 - Pre-Alpha
Classifier: Natural Language :: English
Classifier: Operating System :: MacOS
Classifier: Operating System :: Unix
Classifier: Programming Language :: Python :: 3
Classifier: Programming Language :: Python :: 3.7
Requires-Dist: ruamel.yaml
Requires-Dist: datacustodian (==0.3.2)
